dkube/__init__.py
dkube/pipelines/__init__.py
dkube/pipelines/ops.py
dkube/pipelines/components/__init__.py
dkube/pipelines/components/op.py
dkube/sdk/__init__.py
dkube/sdk/api.py
dkube/sdk/internal/__init__.py
dkube/sdk/internal/api_base.py
dkube/sdk/internal/files_base.py
dkube/sdk/internal/dkube_api/__init__.py
dkube/sdk/internal/dkube_api/api_client.py
dkube/sdk/internal/dkube_api/configuration.py
dkube/sdk/internal/dkube_api/rest.py
dkube/sdk/internal/dkube_api/api/__init__.py
dkube/sdk/internal/dkube_api/api/dfab_api.py
dkube/sdk/internal/dkube_api/api/dkube_api.py
dkube/sdk/internal/dkube_api/api/dkube_operator_exclusive_api.py
dkube/sdk/internal/dkube_api/models/__init__.py
dkube/sdk/internal/dkube_api/models/affinity_model.py
dkube/sdk/internal/dkube_api/models/api_error.py
dkube/sdk/internal/dkube_api/models/api_response.py
dkube/sdk/internal/dkube_api/models/artifact_volume.py
dkube/sdk/internal/dkube_api/models/auth_model.py
dkube/sdk/internal/dkube_api/models/auth_model_github.py
dkube/sdk/internal/dkube_api/models/auth_model_keycloak.py
dkube/sdk/internal/dkube_api/models/auth_model_ldap.py
dkube/sdk/internal/dkube_api/models/auth_model_ldap_advanced.py
dkube/sdk/internal/dkube_api/models/auth_model_local.py
dkube/sdk/internal/dkube_api/models/body.py
dkube/sdk/internal/dkube_api/models/body1.py
dkube/sdk/internal/dkube_api/models/body10.py
dkube/sdk/internal/dkube_api/models/body11.py
dkube/sdk/internal/dkube_api/models/body12.py
dkube/sdk/internal/dkube_api/models/body13.py
dkube/sdk/internal/dkube_api/models/body14.py
dkube/sdk/internal/dkube_api/models/body15.py
dkube/sdk/internal/dkube_api/models/body16.py
dkube/sdk/internal/dkube_api/models/body17.py
dkube/sdk/internal/dkube_api/models/body18.py
dkube/sdk/internal/dkube_api/models/body19.py
dkube/sdk/internal/dkube_api/models/body2.py
dkube/sdk/internal/dkube_api/models/body20.py
dkube/sdk/internal/dkube_api/models/body21.py
dkube/sdk/internal/dkube_api/models/body22.py
dkube-2.2.dist-info/METADATA
dkube-2.2.dist-info/WHEEL
dkube-2.2.dist-info/top_level.txt
dkube-2.2.dist-info/RECORD
