Metadata-Version: 2.1
Name: dkube
Version: 2.2
Summary: Dkube SDK
Home-page: https://github.com/oneconvergence/dkube.git
Author: oneconvergence
Author-email: dkube@oneconvergence.com
License: UNKNOWN
Platform: UNKNOWN
Requires-Python: >3.5
Requires-Dist: validators
Requires-Dist: minio
Requires-Dist: requests
Requires-Dist: kfp (==1.0)
Requires-Dist: certifi (>=14.05.14)
Requires-Dist: six (>=1.10)
Requires-Dist: python-dateutil (>=2.5.3)
Requires-Dist: setuptools (>=21.0.0)
Requires-Dist: urllib3 (>=1.15.1)
Requires-Dist: url-normalize
Requires-Dist: pyarrow
Requires-Dist: pandas
